elecmap/__init__.py
elecmap/electrode_detection.py
elecmap/electrode_visualization.py
elecmap-0.1.1.dist-info/licenses/LICENSE
elecmap-0.1.1.dist-info/METADATA
elecmap-0.1.1.dist-info/WHEEL
elecmap-0.1.1.dist-info/top_level.txt
elecmap-0.1.1.dist-info/RECORD
