Metadata-Version: 2.4
Name: elecmap
Version: 0.1.1
Summary: Detect and visualize intracranial electrode locations from CT and MR scans.
Author-email: Mohammad Saber <mohammadsaber@gmail.com>
License-Expression: MIT
Project-URL: Homepage, https://github.com/saberm2837/ElecMap
Project-URL: Bug Tracker, https://github.com/saberm2837/ElecMap/issues
Keywords: medical imaging,neurology,electrode localization,CT,MR,MRI
Classifier: Programming Language :: Python :: 3
Classifier: Operating System :: OS Independent
Classifier: Topic :: Scientific/Engineering :: Medical Science Apps.
Classifier: Intended Audience :: Science/Research
Classifier: Development Status :: 3 - Alpha
Requires-Python: >=3.8
License-File: LICENSE
Requires-Dist: SimpleITK>=2.1
Requires-Dist: nipype>=1.8
Requires-Dist: numpy>=1.20
Requires-Dist: matplotlib>=3.5
Requires-Dist: termcolor>=2.0
Requires-Dist: tqdm>=4.60
Dynamic: license-file
